MANIFEST.in
README.rst
setup.cfg
setup.py
doc/Makefile
doc/build/doctrees/environment.pickle
doc/build/doctrees/index.doctree
doc/build/doctrees/usage.doctree
doc/build/html/.buildinfo
doc/build/html/genindex.html
doc/build/html/index.html
doc/build/html/objects.inv
doc/build/html/search.html
doc/build/html/searchindex.js
doc/build/html/usage.html
doc/build/html/_sources/index.txt
doc/build/html/_sources/usage.txt
doc/build/html/_static/ajax-loader.gif
doc/build/html/_static/alabaster.css
doc/build/html/_static/basic.css
doc/build/html/_static/classic.css
doc/build/html/_static/comment-bright.png
doc/build/html/_static/comment-close.png
doc/build/html/_static/comment.png
doc/build/html/_static/default.css
doc/build/html/_static/doctools.js
doc/build/html/_static/down-pressed.png
doc/build/html/_static/down.png
doc/build/html/_static/file.png
doc/build/html/_static/jquery-1.11.1.js
doc/build/html/_static/jquery.js
doc/build/html/_static/minus.png
doc/build/html/_static/plus.png
doc/build/html/_static/pydoctheme.css
doc/build/html/_static/pygments.css
doc/build/html/_static/searchtools.js
doc/build/html/_static/sidebar.js
doc/build/html/_static/underscore-1.3.1.js
doc/build/html/_static/underscore.js
doc/build/html/_static/up-pressed.png
doc/build/html/_static/up.png
doc/build/html/_static/websupport.js
doc/source/conf.py
doc/source/index.rst
doc/source/usage.rst
src/logconf/__init__.py
src/logconf/dsl.py
src/logconf/dslbase.py
src/logconf/utils.py
src/logconf/version.py
src/logconf_dsl.egg-info/PKG-INFO
src/logconf_dsl.egg-info/SOURCES.txt
src/logconf_dsl.egg-info/dependency_links.txt
src/logconf_dsl.egg-info/requires.txt
src/logconf_dsl.egg-info/top_level.txt