Metadata-Version: 1.0
Name: logconf-dsl
Version: 1.0b2
Summary: Python logging configuration DSL
Home-page: https://github.com/joar/logconf
Author: Joar Wandborg
Author-email: firstname at lastname dot se
License: MIT
Keywords: logging,configuration,dsl
Platform: UNKNOWN
